fastluks/__init__.py
fastluks/common.py
fastluks/fast_luks_lib.py
fastluks/vault_support.py
fastluks-0.0.32.data/scripts/fastluks
fastluks-0.0.32.data/scripts/luksctl
fastluks-0.0.32.data/scripts/luksctl_api
luksctl/__init__.py
luksctl/luksctl_lib.py
luksctl_api/__init__.py
luksctl_api/app.py
luksctl_api/luksctl_api_master.py
luksctl_api/luksctl_api_wn.py
luksctl_api/luksctl_run.py
luksctl_api/ssl_certificate.py
luksctl_api/vault_support.py
fastluks-0.0.32.dist-info/LICENSE
fastluks-0.0.32.dist-info/METADATA
fastluks-0.0.32.dist-info/WHEEL
fastluks-0.0.32.dist-info/top_level.txt
fastluks-0.0.32.dist-info/RECORD
