Metadata-Version: 2.1
Name: fastluks
Version: 0.0.32
Summary: Storage encryption through LUKS
Home-page: https://github.com/dacolombo/fast-luks-py
Author: Daniele Colombo
Author-email: daniele.colombo39@gmail.com
License: UNKNOWN
Project-URL: Bug Tracker, https://github.com/dacolombo/fast-luks-py/issues
Platform: UNKNOWN
Classifier: Programming Language :: Python :: 3
Classifier: License :: OSI Approved :: MIT License
Requires-Python: >=3.6
License-File: LICENSE
Requires-Dist: zc.lockfile (==2.0)
Requires-Dist: hvac (==0.11.2)
Requires-Dist: distro (==1.3.0)
Requires-Dist: flask (==2.0.0)
Requires-Dist: gunicorn (==20.1.0)
Requires-Dist: cryptography (==36.0.1)
